{
  "id": 22324,
  "title": "Stable isotopes in avian research: a step by step protocol to feather sample preparation for stable isotope analysis of carbon (δ13C), nitrogen (δ15N), and hydrogen (δ2H). Version 1.1",
  "uri": "stable-isotopes-in-avian-research-a-step-by-step-p-z2uf8ew",
  "doi": "dx.doi.org/10.17504/protocols.io.z2uf8ew",
  "description": "{\"blocks\":[{\"key\":\"6336o\",\"text\":\"Summary\",\"type\":\"unstyled\",\"depth\":0,\"inlineStyleRanges\":[{\"style\":\"bold\",\"offset\":0,\"length\":7}],\"entityRanges\":[],\"data\":[]},{\"key\":\"8tplk\",\"text\":\"Using a 2:1 chloroform methanol solution and Versatm detergent diluted with deionized water we cleaned feather samples of oil/debris for stable isotope analysis of carbon (δ13C), nitrogen (δ15N), and hydrogen (δ2H). Prepared samples were then measured, cut, and packaged in tin or silver capsules for analysis of carbon(δ13C) and nitrogen(δ15N) or hydrogen(δ2H), respectively. We aim to standardize the laboratory procedure across institutions and research groups focused on avian ecology and conservation and to improve result accuracy and reproducibility.\",\"type\":\"unstyled\",\"depth\":0,\"inlineStyleRanges\":[{\"style\":\"sup\",\"offset\":50,\"length\":3},{\"style\":\"sup\",\"offset\":173,\"length\":2},{\"style\":\"sup\",\"offset\":190,\"length\":2},{\"style\":\"sup\",\"offset\":211,\"length\":1},{\"style\":\"sup\",\"offset\":321,\"length\":2},{\"style\":\"sup\",\"offset\":340,\"length\":2},{\"style\":\"sup\",\"offset\":358,\"length\":1}],\"entityRanges\":[],\"data\":[]},{\"key\":\"63u0o\",\"text\":\"\",\"type\":\"unstyled\",\"depth\":0,\"inlineStyleRanges\":[],\"entityRanges\":[],\"data\":[]},{\"key\":\"5n4pj\",\"text\":\"\",\"type\":\"unstyled\",\"depth\":0,\"inlineStyleRanges\":[],\"entityRanges\":[],\"data\":[]},{\"key\":\"6b77s\",\"text\":\"Background \",\"type\":\"unstyled\",\"depth\":0,\"inlineStyleRanges\":[{\"style\":\"bold\",\"offset\":0,\"length\":11}],\"entityRanges\":[],\"data\":[]},{\"key\":\"4qq1e\",\"text\":\"Stable isotope analysis of relatively abundant elements such as carbon (δ13C), nitrogen (δ15N), and hydrogen (δ2H) have been widely implemented, particularly over the past two decades, in ecology, conservation, and forensic studies (Vander Zanden et al. 2018.). For example, stable isotope analyses of biological tissues can reveal useful information on diet, trophic level interactions, and large scale animal movements (Bridge et al. 2011; Contina et al. 2013; Zenzal et al. 2018). However, laboratory sample preparation for stable isotope studies requires a standardized protocol to ensure accuracy and repeatability of the results (Paritte and Kelly 2009).\",\"type\":\"unstyled\",\"depth\":0,\"inlineStyleRanges\":[{\"style\":\"sup\",\"offset\":73,\"length\":2},{\"style\":\"sup\",\"offset\":90,\"length\":2},{\"style\":\"sup\",\"offset\":111,\"length\":1}],\"entityRanges\":[],\"data\":[]},{\"key\":\"2akdv\",\"text\":\"\",\"type\":\"unstyled\",\"depth\":0,\"inlineStyleRanges\":[],\"entityRanges\":[],\"data\":[]},{\"key\":\"8mudn\",\"text\":\"Corresponding author: andrea.contina@ucdenver.edu \",\"type\":\"unstyled\",\"depth\":0,\"inlineStyleRanges\":[{\"style\":\"bold\",\"offset\":0,\"length\":20}],\"entityRanges\":[{\"key\":0,\"offset\":22,\"length\":27}],\"data\":[]},{\"key\":\"7hhma\",\"text\":\"\",\"type\":\"unstyled\",\"depth\":0,\"inlineStyleRanges\":[],\"entityRanges\":[],\"data\":[]},{\"key\":\"5qe0e\",\"text\":\"\",\"type\":\"unstyled\",\"depth\":0,\"inlineStyleRanges\":[],\"entityRanges\":[],\"data\":[]},{\"key\":\"4fllb\",\"text\":\"Useful references:\",\"type\":\"unstyled\",\"depth\":0,\"inlineStyleRanges\":[{\"style\":\"bold\",\"offset\":0,\"length\":18}],\"entityRanges\":[],\"data\":[]},{\"key\":\"avk08\",\"text\":\"\",\"type\":\"unstyled\",\"depth\":0,\"inlineStyleRanges\":[],\"entityRanges\":[],\"data\":[]},{\"key\":\"bg62r\",\"text\":\"Zenzal T.J. et al. 2018. Temporal migration patterns between natal locations of ruby-throated hummingbirds (Archilochus colubris) and their Gulf Coast stopover site. Movement ecology, 6(1), p.2.\",\"type\":\"unstyled\",\"depth\":0,\"inlineStyleRanges\":[{\"style\":\"italic\",\"offset\":108,\"length\":20}],\"entityRanges\":[],\"data\":[]},{\"key\":\"el6j1\",\"text\":\"\",\"type\":\"unstyled\",\"depth\":0,\"inlineStyleRanges\":[],\"entityRanges\":[],\"data\":[]},{\"key\":\"firs7\",\"text\":\"Vander Zanden et al. 2018. Application of isoscapes to determine geographic origin of terrestrial wildlife for conservation and management. Biological conservation, 228, pp.268-280.\",\"type\":\"unstyled\",\"depth\":0,\"inlineStyleRanges\":[],\"entityRanges\":[],\"data\":[]},{\"key\":\"9udlt\",\"text\":\" \",\"type\":\"unstyled\",\"depth\":0,\"inlineStyleRanges\":[],\"entityRanges\":[],\"data\":[]},{\"key\":\"6in2t\",\"text\":\"Contina et al. 2013. Using geologgers to investigate bimodal isotope patterns in Painted Buntings (Passerina ciris). The Auk, 130(2), pp.265-272.\",\"type\":\"unstyled\",\"depth\":0,\"inlineStyleRanges\":[{\"style\":\"italic\",\"offset\":99,\"length\":15}],\"entityRanges\":[],\"data\":[]},{\"key\":\"crh9t\",\"text\":\" \",\"type\":\"unstyled\",\"depth\":0,\"inlineStyleRanges\":[],\"entityRanges\":[],\"data\":[]},{\"key\":\"99mii\",\"text\":\"Bridge et al. 2011. Causes of bimodal stable isotope signatures in the feathers of a molt-migrant songbird. Canadian Journal of Zoology, 89(10), pp.951-959.\",\"type\":\"unstyled\",\"depth\":0,\"inlineStyleRanges\":[],\"entityRanges\":[],\"data\":[]},{\"key\":\"19dti\",\"text\":\" \",\"type\":\"unstyled\",\"depth\":0,\"inlineStyleRanges\":[],\"entityRanges\":[],\"data\":[]},{\"key\":\"4dl3d\",\"text\":\"Paritte and Kelly 2009. Effect of cleaning regime on stable-isotope ratios of feathers in Japanese Quail (Coturnix japonica). The Auk, 126(1), pp.165-174.\",\"type\":\"unstyled\",\"depth\":0,\"inlineStyleRanges\":[{\"style\":\"italic\",\"offset\":106,\"length\":17}],\"entityRanges\":[],\"data\":[]}],\"entityMap\":{\"0\":{\"type\":\"link\",\"mutability\":\"\",\"data\":{\"guid\":\"D64288F563554EDFA280581DDA395B69\",\"url\":\"mailto:andrea.contina@ucdenver.edu\"}}}}",
  "guidelines": "{\"blocks\":[{\"key\":\"f28vg\",\"text\":\"Anytime work with samples is being performed, latex or nitrile gloves should be worn to prevent contamination from outside substances. All work should be performed on a flat, cleaned surface.\",\"type\":\"unstyled\",\"depth\":0,\"inlineStyleRanges\":[],\"entityRanges\":[],\"data\":[]},{\"key\":\"a676l\",\"text\":\"\",\"type\":\"unstyled\",\"depth\":0,\"inlineStyleRanges\":[],\"entityRanges\":[],\"data\":[]},{\"key\":\"6qin\",\"text\":\"Some steps in this protocol, such as standard weights and data sheets, might be idiosyncratic to our lab and equipment used at the time of the analysis. Please contact andrea.contina@ucdenver.edu if you have any questions or comments.\",\"type\":\"unstyled\",\"depth\":0,\"inlineStyleRanges\":[],\"entityRanges\":[{\"key\":0,\"offset\":168,\"length\":27}],\"data\":[]}],\"entityMap\":{\"0\":{\"type\":\"link\",\"mutability\":\"\",\"data\":{\"guid\":\"31C245BC4EA04962ACD6895B59BCBA69\",\"url\":\"mailto:andrea.contina@ucdenver.edu\"}}}}",
  "before_start": "",
  "warning": "{\"blocks\":[{\"key\":\"ckuqg\",\"text\":\"When combining Chloroform and Methanol, only open containers under a fume hood. Latex or Nitrile gloves should be worn when handling substances. Protective eyewear should also be worn.\",\"type\":\"unstyled\",\"depth\":0,\"inlineStyleRanges\":[],\"entityRanges\":[],\"data\":[]}],\"entityMap\":{}}",
  "materials_text": "{\"blocks\":[{\"key\":\"znm4u\",\"text\":\"MATERIALS\",\"type\":\"unstyled\",\"depth\":0,\"inlineStyleRanges\":null,\"entityRanges\":null,\"data\":null},{\"key\":\"9OdM7\",\"text\":\" \",\"type\":\"unstyled\",\"depth\":0,\"inlineStyleRanges\":null,\"entityRanges\":[{\"key\":0,\"offset\":0,\"length\":1}],\"data\":null},{\"key\":\"BWYwr\",\"text\":\" \",\"type\":\"unstyled\",\"depth\":0,\"inlineStyleRanges\":null,\"entityRanges\":[{\"key\":1,\"offset\":0,\"length\":1}],\"data\":null},{\"key\":\"FaMjD\",\"text\":\" \",\"type\":\"unstyled\",\"depth\":0,\"inlineStyleRanges\":null,\"entityRanges\":[{\"key\":2,\"offset\":0,\"length\":1}],\"data\":null},{\"key\":\"RcTBg\",\"text\":\" \",\"type\":\"unstyled\",\"depth\":0,\"inlineStyleRanges\":null,\"entityRanges\":[{\"key\":3,\"offset\":0,\"length\":1}],\"data\":null},{\"key\":\"u5Vaf\",\"text\":\" \",\"type\":\"unstyled\",\"depth\":0,\"inlineStyleRanges\":null,\"entityRanges\":[{\"key\":4,\"offset\":0,\"length\":1}],\"data\":null},{\"key\":\"7Ag31\",\"text\":\" \",\"type\":\"unstyled\",\"depth\":0,\"inlineStyleRanges\":null,\"entityRanges\":[{\"key\":5,\"offset\":0,\"length\":1}],\"data\":null},{\"key\":\"fgolp\",\"text\":\"These are the standards used for Hydrogen analysis in our lab: KHS (Kudu Horn Standard), CBS (Caribou Hoof Standard), BHCO (Brown-headed Cowbird). Standards used for Carbon and Nitrogen analysis in our lab: USGS40, USGS41a, and USGS 42. USGS 42 can be used for the reference curve and QAQC.Note: different standards, capsules, and weights are used for Carbon and Nitrogen (see Table 1 below). Other materials: Staples Compressed-gas duster.\",\"type\":\"unstyled\",\"depth\":0,\"inlineStyleRanges\":[{\"style\":\"italic\",\"offset\":124,\"length\":23},{\"style\":\"bold\",\"offset\":290,\"length\":120}],\"entityRanges\":[],\"data\":[]}],\"entityMap\":{\"0\":{\"type\":\"reagents\",\"mutability\":\"\",\"data\":{\"id\":2905,\"guid\":\"4104F027341F11EE9D4302C0B41BC903\",\"name\":\"Chloroform\",\"mol_weight\":119.37,\"sku\":\"\",\"url\":\"\",\"cas_number\":\"\",\"rrid\":\"\",\"vendor\":{\"id\":1,\"name\":\"Contributed by users\",\"link\":\"https://www.protocols.io\",\"is_requested\":false,\"image\":{\"source\":\"/img/vendors/1.png\",\"placeholder\":\"/img/vendors/1.png\"}},\"is_public\":true,\"can_edit\":false}},\"1\":{\"type\":\"reagents\",\"mutability\":\"\",\"data\":{\"id\":4700,\"guid\":\"41078CFA341F11EE9D4302C0B41BC903\",\"name\":\"Ethanol\",\"mol_weight\":0,\"sku\":\"\",\"url\":\"\",\"cas_number\":\"\",\"rrid\":\"\",\"vendor\":{\"id\":1,\"name\":\"Contributed by users\",\"link\":\"https://www.protocols.io\",\"is_requested\":false,\"image\":{\"source\":\"/img/vendors/1.png\",\"placeholder\":\"/img/vendors/1.png\"}},\"is_public\":true,\"can_edit\":false}},\"2\":{\"type\":\"reagents\",\"mutability\":\"\",\"data\":{\"id\":116665,\"guid\":\"4192A0C2341F11EE9D4302C0B41BC903\",\"name\":\"Methanol\",\"mol_weight\":0,\"sku\":\"\",\"url\":\"\",\"cas_number\":\"\",\"rrid\":\"\",\"vendor\":{\"id\":1,\"name\":\"Contributed by users\",\"link\":\"https://www.protocols.io\",\"is_requested\":false,\"image\":{\"source\":\"/img/vendors/1.png\",\"placeholder\":\"/img/vendors/1.png\"}},\"is_public\":true,\"can_edit\":false}},\"3\":{\"type\":\"reagents\",\"mutability\":\"\",\"data\":{\"id\":118994,\"guid\":\"41978808341F11EE9D4302C0B41BC903\",\"name\":\"double distilled water (ddH2O)\",\"mol_weight\":0,\"sku\":\"\",\"url\":\"\",\"cas_number\":\"\",\"rrid\":\"\",\"vendor\":{\"id\":1,\"name\":\"Contributed by users\",\"link\":\"https://www.protocols.io\",\"is_requested\":false,\"image\":{\"source\":\"/img/vendors/1.png\",\"placeholder\":\"/img/vendors/1.png\"}},\"is_public\":true,\"can_edit\":false}},\"4\":{\"type\":\"reagents\",\"mutability\":\"\",\"data\":{\"id\":182912,\"guid\":\"41AA9CE1341F11EE9D4302C0B41BC903\",\"name\":\"Versa-Clean Multi-Purpose Cleaner\",\"mol_weight\":0,\"sku\":\"04-342\",\"url\":\"https://fscimage.fishersci.com/msds/45385.htm\",\"cas_number\":\"\",\"rrid\":\"\",\"vendor\":{\"id\":31,\"name\":\"Fisher Scientific\",\"link\":\"https://www.fishersci.com/us/en/home.html\",\"is_requested\":false,\"image\":{\"source\":\"/img/vendors/placeholder.png\",\"placeholder\":\"/img/vendors/placeholder.png\"}},\"is_public\":true,\"can_edit\":false}},\"5\":{\"type\":\"reagents\",\"mutability\":\"\",\"data\":{\"id\":182913,\"guid\":\"41AA9D33341F11EE9D4302C0B41BC903\",\"name\":\"Kimwipes\",\"mol_weight\":0,\"sku\":\"34120\",\"url\":\"https://www.fishersci.com/shop/products/kimberly-clark-kimtech-science-kimwipes-delicate-task-wipers-7/p-211240\",\"cas_number\":\"\",\"rrid\":\"\",\"vendor\":{\"id\":346,\"name\":\"Kimberly-Clark\",\"link\":\"http://www.kimberlyclarkprofessional.com\",\"is_requested\":false,\"image\":{\"source\":\"/img/vendors/placeholder.png\",\"placeholder\":\"/img/vendors/placeholder.png\"}},\"is_public\":true,\"can_edit\":false}}}}",
  "steps": [
    "Under fume hood, pour 100mL chloroform into clean 250 mL beaker.",
    "Pour 50mL methanol into beaker.",
    "Stir contents with a stir rod, or carefully swirl contents of container under fume hood to mix contents.",
    "If desired for repeated use, pour 2:1 chloroform methanol solution into at least 250mL container with sealable, non-plastic lid.",
    "In clean 250mL beaker, pour 150mL deionized water , and 5mL detergent .",
    "Gently swirl content of container.",
    "Avoid agitating solution in any manner which might generate bubbles.",
    "Mark beaker DETERGENT.",
    "Into three clean 250mL beakers, pour 200mL deionized water each.",
    "Mark Beakers 1, 2, and 3.",
    "Place beakers in order DETERGENT, 1, 2, 3. Feathers will be cleaned in this order to avoid final prepared feather being contaminated with detergent. Beakers",
    "Using calipers, measure the length of the feather, starting from the tip of the quill (calamus) to the end of the rachis or farthest barb. Record the weight of the feather with balance. Measuring the length of the feather Weighting the feather",
    "Using a razor that has been cleaned with ethanol, cut off the calamus of the feather as indicated below: The dashed line indicates where the calamus should be cut. Schematic feather parts",
    "It is useful to use one hand to hold down the feather by placing the gloved base of your hand against the end of the feather and holding the calamus with forceps when cutting the calamus, this prevents the calamus from being lost. (technique pictured above)",
    "The calamus is removed to later acquire DNA from the feather.",
    "Place separated calamus into marked and clean paper envelope , to absorb humidity, and seal envelope with adhesive to ensure calamus is retained. Label the clean envelope with banding ID number, location, species, sex, and date of collection.",
    "With clean paper towels, prepare in advance a drying “bed” for feathers by layering the paper towels over one another.",
    "Using forceps, hold the rachis of the feather so that the feather is perpendicular to the forceps. Under a fume hood, dip the feather into a 2:1 (chloroform methanol) solution. Holding the rachis of the feather with forceps Working under a fume hood",
    "Agitate the feather to make stirring motions with the feather for 30 seconds.",
    "After each feather has been washed in 2:1 (chloroform methanol) solution , place each feather on dry cloth or paper towel, next to clean envelopes showing feather details and individual IDs. Drying feathers on paper towel next to clean envelopes showing feathers ID",
    "Allow feather to dry for 24-36 hours or until completely dry.",
    "Please note: 24-36 hours was at room temperature of 26C near the room&#39;s heating system. This may have reduced drying time in our lab.",
    "With clean forceps, pick up each feather from the drying bed and dip into solution of 30:1 water to detergent (prepared from Steps 5-10 above.) Beakers",
    "Agitate each feather for 30 seconds to ensure thorough cleaning.",
    "After 30 seconds of cleaning remove the feather from 30:1 water to detergent solution with forceps, and place each feather into the container of deionized water (first beaker, labelled &#34;1.&#34;)",
    "Agitate feather for 30 seconds.",
    "Repeat step 21-22 two additional times with separate beakers of deionized clean water (beakers &#34;2&#34;, and &#34;3.&#34;)",
    "Note: ensure the order of containers (beakers) is kept the same for every feather to ensure all detergent is removed from each feather.",
    "Place each cleaned feather onto paper towel to dry, and transfer marked envelopes from Step 6 to place adjacent to each feather to keep track of samples.",
    "Ensure every feather is next to its respective envelope (label), and that the placement of each feather relative to its labelled envelope is kept the same for every feather, to ensure the feathers details are not mistaken.",
    "Allow feather to dry for 24-36 hours or until completely dry.",
    "Place each feather into its respective clean labelled envelope, and store cleaned envelopes into separate container.",
    "Clean three sets of forceps and a spatula with 95% ethanol by staurating a kimwipe TM with ethanol and rubbing all used surfaces of the instrument. Place instrument under lamp or in direct light to evaporate ethanol.",
    "Using air duster, or similar cleaning product, clear surface of microbalance, and remove any particles from previous uses. Ensure chamber is clean, no residuals remain from previous uses.",
    "Air duster will remove particles from chamber.",
    "Using forceps, place a 3.5x5mm silver capsule, open end up, into the center of a microbalance.",
    "Bent tip forceps are preferred for this step.",
    "Close microbalance chamber and tare microbalance to empty silver capsule mass.",
    "With spatula, pick up a very small quantity (as shown in the photo) of BHCO, KHS, or CBS standard. Small quantity of BHCO standard",
    "REMEMBER: silver capsules are used for hydrogen isotope analysis, tin capsules are used for carbon and nitrogen isotope analysis. Please see Table 1 below for further details on standards and weights for different isotopes. This is crucial! Table 1. Details on standards, capsules and weights for different isotopes used at the University of Oklahoma. Weights might need to be adjusted depending on species and laboratory equipment.",
    "Open microbalance chamber, and hold spatula with standard over open capsule. Use second pair of forceps to push small quantities of standard off of the end of the spatula into the capsule. Microbalance chamber with open silver capsule being filled with BHCO standard",
    "Remove spatula and forceps from balance chamber, and close draft shield doors.",
    "If mass of standard is below required standard mass, repeat steps 32-33, else proceed to step 35.",
    "If mass of standard is above required mass, use bent tip forcepts to hold capsule, and second pair of forceps to remove tiny excess of standard and place into waste receptacle.",
    "Once desired mass is achieved , record mass on data sheet (see below for data sheet template) , and use bent tip forceps to remove capsule from microbalance. Place capsule on clean flat surface.",
    "Using the tip of a third pair of forceps, push the opened end of the capsule so it gets closed (sealed), and continue to hold end closed with forceps.",
    "With a gloved hand very gently squeeze the base of the capsule between thumb and forefinger until capsule is completely flat. If you squeeze too quickly, you might damage the capsule and disperse the standard.",
    "Using forceps holding the end of the capsule, place the capsule flat end down on a clean, dry surface, and rotate forcepts 180 degrees in the direction of the rest of the capsule, creating a curved section of the capsule in the place of the opening.",
    "Gently ungrasp the end of capsule with forceps, and regrasp the capsule with the inside of one arm of the forceps on outside of the end of the curved portion of capsule, and the inside portion of the other arm of the forceps on the nearest flat portion of the capsule to the newly formed curved section. Squeeze the forceps to make a fold in the capsule.",
    "Repeat steps 39 and 40 until capsule is approximately twice the width of the forceps in length. Fold any remaining capsule over the folded portion of the capsule.",
    "Place the now folded capsule on a flat, clean, dry surface, and place the forceps around the capsule such that the inside of the arms fo the forceps have greater hight than the capsule, and the angle between the capsule sides and the forcep arms is minimized. Squeeze the arms of the forceps gently, to compact the capsule along its width. Make the capsule as round-ish as possible.",
    "If necessary, rotate the capsule 90 degrees, and repeat step 42. Repeat this step until every oientation of the caspule has been pressed an equal number of times.",
    "This ensures the capsule maintains a relatively cubic or round-ish shape.",
    "If necessary, pick up the foceps and place the outside surface of one arm of the forceps onto the topmost surface of the capsule. Press the forceps so the capsule is pressed evenly along its topmost surface.",
    "Repeat steps 43-44 until capsule has relatively smooth surfaces and is cubic or round-ish. There should not be tears in the surface of the capsule or any sections of the capsule that extend out beyond the rest of the cubic or round-ish shape.",
    "If any tearing occurs , or if the capsule is dropped onto an uncleaned surface at any time, place the compromised capsule into a waste receptacle, and restart the process with a fresh capsule.",
    "When the capsule is to the desired dimensions, use a pair of forceps to place the capsule into its designated well on the tray. Record what well the capsule has been placed into (e.g. A6 , or C5 , etc.) on a data sheet, along with the final weight , sample ID , and any other relavant information.",
    "Clean two sets of forceps and a razor blade with 95% ethanol by saturating a kimwipe TM with ethanol and rubbing all used surfaces of the instruments. Place instruments under lamp or another direct light source to evaporate ethanol.",
    "Using air duster, or similar cleaning product, clear surface of microbalance.",
    "With clean razor blade, cut off a portion of the tip of the now cleaned and dried feather (the point opposite the calamus) to be sampled for stable isotope analysis . Cutting off a portion of the tip of the cleaned feather",
    "The method of cutting is not important, but how the feather is cut should remain consistent between feather samples. We recommend cutting from the rachis, and using the barbs attached to the incised rachis. Note that different sections of the rachis might introduce variation stable isotope values (particularly for longer feathers) and we recommend to be consistent across feather samples with the tip and rachis section being used for analysis.",
    "Using forceps, gently separate the clipped part of the rachis and any attached barbs from the rest of the feather.",
    "Using clean forceps, place feather on tared balance, and close balance shields.",
    "If the feather is above desired mass, use clean razor to cut off an additional portion of the feather. Using same forceps as in the previous step, place the feather on the balance. Repeat as needed until weight is within desired parameters ( +/- 10 µg. )",
    "If the feather is above desired mass, using same forceps as step 51, remove the feather from balance, and use a clean razor to remove small portions of the sample.",
    "If sample is close to desired mass, barbs can be used for finer adjustment of mass, while removal of rachis will produce a larger change in mass.",
    "If sample is within desired mass, remove from balance with forceps, and place onto clean surface.",
    "Using clean bent forceps, place empty capsule onto balance and tare balance.",
    "Remove capsule from balance, with clean forceps, place sample inside the capsule.",
    "It may be necessary to separate the feather sample into smaller subsections with a razor in order to fit into capsule.",
    "Be careful that portions of the sample are not protruding from the capsule by static electricity.",
    "When all portions of sample are inside capsule, use bent forceps to place capsule with sample into balance.",
    "If readout of balance does not match original mass, check razor, forceps, and cutting surface for portions of sample that may have been ejected form capsule or that may have adhered to instruments. Use forceps to transfer these sample portions into capsule.",
    "Once desired mass is acheived, record mass on data sheet together with sample ID, and use bent tip forceps to remove capsule from microbalance. Place capsule on clean flat surface.",
    "Using the tip of a pair of forceps, push the open end of the capsule closed, and continue to hold end closed with forceps. Closing the silver capsule from the top",
    "With a gloved hand gently squeeze the base of the capsule between thumb and forefinger until the capsule is flat. Do not damage the capsule .",
    "Using forceps, holding the end of the capsule, place the capsule flat end down on a clean, dry surface, and rotate forceps 180 degrees to form a curved section of the capsule. Folding the silver capsule",
    "Gently ungrasp end of capsule with forceps, and regrasp capsule with the inside of one arm of the forcep on the end of the curved portion of the capsule, and the inside protion of the other arm of the forcep on the nearest flat portion of the capsule to the newly formed curved section. Squeeze the forceps to make a fold in the capsule.",
    "Repeat steps 62 and 63 until capsule is approximately twice the width of the forceps in length. Fold any remaining capsule over the folded portion of the capsule.",
    "Using a third pair of forceps, grab one of the ends of the capsule and repeat steps 64 along the width of the capsule until capsule approaches desired shape for analysis. Schematic representation of the folding capsule process",
    "Place now foldd capsule on a flat, clean, dry surface, and place the forceps around the capsule such that the inside of the arms of the forceps have a greater height thtan the capsule, and the angle between the capsule sides and the forceps is a minimum. Squeeze the arms of the forceps gently, to compact the capsule along its width. Final folded round-ish capsule",
    "Rotate the capsule 90 degrees, and repeat step 66.",
    "Rotate capsule after every compression fo ensure a relatively cubic or rectangular or round-ish shape.",
    "Pick up the forceps and place the outside surface of one arm of the forceps onto the topmost surface of the capsule. Press the forceps so that the capsule is pressed evenly along its topmost surface. See photo above.",
    "Repeat steps 67-68 until the capsule has relatively smooth sides, and is cubic or round-ish in shape. There should be no tears in the surface of the capsule.",
    "If tearing occurs, or if the capsule is droppe donto an uncleaned surface at any time, place the compromised capsule into a waste receptacle, and restart the process with a fresh capsule.",
    "Once the capsule is completely pressd, pick up the capsule with clean forceps and place the capsule into designated well. Record well position (e.g. A6 , or C7 , etc.), next to sample weight, sample ID, and tray identification number and species. REMEMBER : Print this data sheet and always keep it attached to the plastic tray that will be used to transport the samples to the mass-spec lab. Keep track of the samples! IMPORTANT : the sequence of the samples and standards matters, we recommend to follow the examples below. Example of data sheet for Hydrogen (see Table 1) Data sheet template (for Hydrogen) used at the University of Oklahoma. Alternate standards and samples following the order indicated on the data sheet. Label everything as best as you can and keep track of the samples, standards, and trays. Weights might need to be adjusted depending on species and laboratory equipment. Example of data sheet for Carbon and Nitrogen (see Table 1) Data sheet template (for Carbon and Nitrogen) used at the University of Oklahoma. Alternate standards and samples following the order indicated on the data sheet. Label everything as best as you can and keep track of the samples, standards, and trays. Note “ nothing ” and “ empty tin ” in tray wells A1 and A2, respectively. Weights might need to be adjusted depending on species and laboratory equipment."
  ],
  "authors": [
    "Brian Chew",
    "Jeff Kelly",
    "Andrea Contina"
  ],
  "creator": "Brian Chew",
  "published_on": 1568465198,
  "created_on": 1555122252,
  "keywords": []
}