{
  "id": 43300,
  "title": "Top-down proteomics data analysis on the NRTDP TDPortal",
  "uri": "top-down-proteomics-data-analysis-on-the-nrtdp-tdp-bnicmcaw",
  "doi": "dx.doi.org/10.17504/protocols.io.bnicmcaw",
  "description": "{\"blocks\":[{\"key\":\"6co55\",\"text\":\"This method describes how to analyze data on TD Portal, a top-down proteomics search tool from the National Resource for Translational and Developmental Proteomics.\",\"type\":\"unstyled\",\"depth\":0,\"inlineStyleRanges\":[],\"entityRanges\":[],\"data\":[]}],\"entityMap\":{}}",
  "guidelines": "",
  "before_start": "",
  "warning": "",
  "materials_text": "",
  "steps": [
    "Top-down proteomics data was searched on the TD Portal (portal.nrtdp.northwestern.edu)",
    "Raw files for analysis were selected for search using Top Down Search v. 4.0.",
    "Search parameters: Organism: Homo Sapiens (Human) with Curated Histones: (Taxon 9606 - June 2020) Use Empirical P-Score: FALSE Filter by FDR: TRUE Create SAS Input Sheet for Quant: FALSE Precursor Resolution: High Resolution Fragmentation Type: Auto Code Set: Standard 4.0.0 Include ProSight Error Tolerant Search: FALSE"
  ],
  "authors": [
    "Jeannie Camarillo",
    "Neil Kelleher"
  ],
  "creator": "Kelleher KRG KRG Research Group",
  "published_on": 1646167349,
  "created_on": 1602867329,
  "keywords": []
}