{
  "id": 93764,
  "title": "Nuclei Isolation from human cortical tissue for enrichment of endothelial and microglial cells",
  "uri": "nuclei-isolation-from-human-cortical-tissue-for-en-c7tczniw",
  "doi": "dx.doi.org/10.17504/protocols.io.5qpvo344zv4o/v1",
  "description": "{\"blocks\":[{\"key\":\"4o5t1\",\"text\":\"This protocol of nuclei Isolation from human cortical tissue is enriched for isolation of endothelial \\u0026 microglial cells\",\"type\":\"unstyled\",\"depth\":0,\"inlineStyleRanges\":[{\"style\":\"bold\",\"offset\":0,\"length\":120}],\"entityRanges\":[],\"data\":{}}],\"entityMap\":{}}",
  "guidelines": "{\"blocks\":[{\"key\":\"3cdt2\",\"text\":\"Use standard BSL-2 precautions when working with human brain samples. \",\"type\":\"unordered-list-item\",\"depth\":0,\"inlineStyleRanges\":[],\"entityRanges\":[],\"data\":{}},{\"key\":\"c290o\",\"text\":\"Fresh frozen brain tissue could be a potential source of infectious agents. Wear proper PPE, including gloves, mask,\\nand lab coat if outside hood. Disposable gown, goggles, or face shield if possible. \",\"type\":\"unordered-list-item\",\"depth\":0,\"inlineStyleRanges\":[],\"entityRanges\":[],\"data\":{}},{\"key\":\"cm64s\",\"text\":\"Decontaminate every reusable equipment (homogenizers) with 25% bleach. Apply RNASe Zap to all surfaces in use.\",\"type\":\"unordered-list-item\",\"depth\":0,\"inlineStyleRanges\":[],\"entityRanges\":[],\"data\":{}},{\"key\":\"ahevp\",\"text\":\"All discarded tissue remnants should go into 10-20% bleach for at least one hour before disposal.\",\"type\":\"unordered-list-item\",\"depth\":0,\"inlineStyleRanges\":[],\"entityRanges\":[],\"data\":{}},{\"key\":\"1kb9e\",\"text\":\"All waste is to be collected and disposed. Discarded tubes and tips go into a biohazard waste bag/box.\",\"type\":\"unordered-list-item\",\"depth\":0,\"inlineStyleRanges\":[],\"entityRanges\":[],\"data\":{}}],\"entityMap\":{}}",
  "before_start": "",
  "warning": "",
  "materials_text": "{\"blocks\":[{\"key\":\"92sr2\",\"text\":\" \",\"type\":\"unstyled\",\"depth\":0,\"inlineStyleRanges\":[],\"entityRanges\":[],\"data\":{}},{\"key\":\"5stk1\",\"text\":\"Prepare the following: (note that these volumes are\\n     optimized for 4 mL centrifuge tubes, * Stock solutions should be prepared the\\n     day before and not used for longer than a week)\",\"type\":\"ordered-list-item\",\"depth\":0,\"inlineStyleRanges\":[],\"entityRanges\":[],\"data\":{}},{\"key\":\"477vr\",\"text\":\" \",\"type\":\"align-justify\",\"depth\":0,\"inlineStyleRanges\":[],\"entityRanges\":[],\"data\":{}},{\"key\":\"aruus\",\"text\":\" \",\"type\":\"atomic\",\"depth\":0,\"inlineStyleRanges\":[],\"entityRanges\":[{\"key\":0,\"offset\":0,\"length\":1}],\"data\":{}},{\"key\":\"tejo\",\"text\":\" \",\"type\":\"align-justify\",\"depth\":0,\"inlineStyleRanges\":[],\"entityRanges\":[],\"data\":{}},{\"key\":\"d6ie0\",\"text\":\" \",\"type\":\"align-justify\",\"depth\":0,\"inlineStyleRanges\":[],\"entityRanges\":[],\"data\":{}},{\"key\":\"c8q1k\",\"text\":\" \",\"type\":\"align-justify\",\"depth\":0,\"inlineStyleRanges\":[],\"entityRanges\":[],\"data\":{}},{\"key\":\"78ubi\",\"text\":\"\",\"type\":\"unstyled\",\"depth\":0,\"inlineStyleRanges\":[],\"entityRanges\":[],\"data\":{}},{\"key\":\"1iu37\",\"text\":\" \",\"type\":\"atomic\",\"depth\":0,\"inlineStyleRanges\":[],\"entityRanges\":[{\"key\":1,\"offset\":0,\"length\":1}],\"data\":{}},{\"key\":\"cfbgv\",\"text\":\"\",\"type\":\"unstyled\",\"depth\":0,\"inlineStyleRanges\":[],\"entityRanges\":[],\"data\":{}},{\"key\":\"d4ei6\",\"text\":\" \",\"type\":\"align-justify\",\"depth\":0,\"inlineStyleRanges\":[{\"style\":\"UNDERLINE\",\"offset\":0,\"length\":1}],\"entityRanges\":[],\"data\":{}},{\"key\":\"6h22q\",\"text\":\"\",\"type\":\"unstyled\",\"depth\":0,\"inlineStyleRanges\":[],\"entityRanges\":[],\"data\":{}},{\"key\":\"duu7q\",\"text\":\" \",\"type\":\"atomic\",\"depth\":0,\"inlineStyleRanges\":[],\"entityRanges\":[{\"key\":2,\"offset\":0,\"length\":1}],\"data\":{}},{\"key\":\"38b99\",\"text\":\"\",\"type\":\"unstyled\",\"depth\":0,\"inlineStyleRanges\":[],\"entityRanges\":[],\"data\":{}},{\"key\":\"fiofg\",\"text\":\" \",\"type\":\"align-justify\",\"depth\":0,\"inlineStyleRanges\":[{\"style\":\"UNDERLINE\",\"offset\":0,\"length\":1}],\"entityRanges\":[],\"data\":{}},{\"key\":\"36o7b\",\"text\":\"\",\"type\":\"unstyled\",\"depth\":0,\"inlineStyleRanges\":[],\"entityRanges\":[],\"data\":{}},{\"key\":\"9236k\",\"text\":\" \",\"type\":\"atomic\",\"depth\":0,\"inlineStyleRanges\":[],\"entityRanges\":[{\"key\":3,\"offset\":0,\"length\":1}],\"data\":{}},{\"key\":\"d22ks\",\"text\":\"\",\"type\":\"unstyled\",\"depth\":0,\"inlineStyleRanges\":[],\"entityRanges\":[],\"data\":{}},{\"key\":\"2fp9q\",\"text\":\" \",\"type\":\"align-justify\",\"depth\":0,\"inlineStyleRanges\":[{\"style\":\"UNDERLINE\",\"offset\":0,\"length\":1}],\"entityRanges\":[],\"data\":{}},{\"key\":\"1ihof\",\"text\":\" \",\"type\":\"atomic\",\"depth\":0,\"inlineStyleRanges\":[],\"entityRanges\":[{\"key\":4,\"offset\":0,\"length\":1}],\"data\":{}},{\"key\":\"lloq\",\"text\":\" Appendix. Solutions:\",\"type\":\"unstyled\",\"depth\":0,\"inlineStyleRanges\":[{\"style\":\"bold\",\"offset\":1,\"length\":20}],\"entityRanges\":[],\"data\":{}},{\"key\":\"akf3d\",\"text\":\"\\n \",\"type\":\"unstyled\",\"depth\":0,\"inlineStyleRanges\":[],\"entityRanges\":[],\"data\":{}},{\"key\":\"8tcfa\",\"text\":\"Stock\\n     Optiprep 60% Iodixanol [Sigma-Aldrich D1556-250mL]\",\"type\":\"ordered-list-item\",\"depth\":0,\"inlineStyleRanges\":[{\"style\":\"UNDERLINE\",\"offset\":0,\"length\":34}],\"entityRanges\":[],\"data\":{}},{\"key\":\"3ohi8\",\"text\":\"\\n \",\"type\":\"unstyled\",\"depth\":0,\"inlineStyleRanges\":[],\"entityRanges\":[],\"data\":{}},{\"key\":\"f8v0g\",\"text\":\"Dilutant:\",\"type\":\"ordered-list-item\",\"depth\":0,\"inlineStyleRanges\":[{\"style\":\"UNDERLINE\",\"offset\":0,\"length\":9}],\"entityRanges\":[],\"data\":{}},{\"key\":\"746lf\",\"text\":\"\\n \\n  \",\"type\":\"unstyled\",\"depth\":0,\"inlineStyleRanges\":[],\"entityRanges\":[],\"data\":{}},{\"key\":\"9m214\",\"text\":\"Final\\n      Concentrations: 900 mM KCL; 30 mM MgCl2; 120 mM Tricine-KOH\\n      (pH 7.8)\",\"type\":\"ordered-list-item\",\"depth\":1,\"inlineStyleRanges\":[{\"style\":\"sub\",\"offset\":50,\"length\":1}],\"entityRanges\":[],\"data\":{}},{\"key\":\"foms8\",\"text\":\"\\n  \",\"type\":\"unstyled\",\"depth\":1,\"inlineStyleRanges\":[],\"entityRanges\":[],\"data\":{}},{\"key\":\"6f7j0\",\"text\":\"Recipe\\n      for 50 mls\",\"type\":\"ordered-list-item\",\"depth\":1,\"inlineStyleRanges\":[],\"entityRanges\":[],\"data\":{}},{\"key\":\"5448l\",\"text\":\"\\n \",\"type\":\"unstyled\",\"depth\":1,\"inlineStyleRanges\":[],\"entityRanges\":[],\"data\":{}},{\"key\":\"slii\",\"text\":\"1)     22.5 ml of 2M KCL, +\",\"type\":\"align-justify\",\"depth\":0,\"inlineStyleRanges\":[],\"entityRanges\":[],\"data\":{}},{\"key\":\"a9vuv\",\"text\":\"2)    1.5 ml of 1M MgCl2, + \",\"type\":\"align-justify\",\"depth\":0,\"inlineStyleRanges\":[],\"entityRanges\":[],\"data\":{}},{\"key\":\"cnm8m\",\"text\":\"3)    6 ml of 1 M Tricine-KOH \",\"type\":\"align-justify\",\"depth\":0,\"inlineStyleRanges\":[],\"entityRanges\":[],\"data\":{}},{\"key\":\"upk0\",\"text\":\"4)    brought up to 50 ml with molecular biology grade water. \",\"type\":\"align-justify\",\"depth\":0,\"inlineStyleRanges\":[],\"entityRanges\":[],\"data\":{}},{\"key\":\"1kvq3\",\"text\":\"\\n \\n  \",\"type\":\"unstyled\",\"depth\":0,\"inlineStyleRanges\":[],\"entityRanges\":[],\"data\":{}},{\"key\":\"e51ml\",\"text\":\"Components\",\"type\":\"ordered-list-item\",\"depth\":1,\"inlineStyleRanges\":[],\"entityRanges\":[],\"data\":{}},{\"key\":\"8rgau\",\"text\":\"\\n \",\"type\":\"unstyled\",\"depth\":1,\"inlineStyleRanges\":[],\"entityRanges\":[],\"data\":{}},{\"key\":\"qlsu\",\"text\":\"1)    Tricine-KOH is 17.92 grams Tricine (Sigma T0377) and 100 mL RNAse\\nfree water for 1 M solution (pH to 7.8 with KOH as needed.  Usually takes about 3-4 mL\\nof 3M KOH).\",\"type\":\"align-justify\",\"depth\":0,\"inlineStyleRanges\":[],\"entityRanges\":[],\"data\":{}},{\"key\":\"cjh1s\",\"text\":\"2)    1 M MgCl2 (AM9530G) and 2M KCl (AM9460G) are commercial RNAse free stocks from\\nAmbion.\",\"type\":\"align-justify\",\"depth\":0,\"inlineStyleRanges\":[],\"entityRanges\":[],\"data\":{}},{\"key\":\"e69qi\",\"text\":\" \",\"type\":\"align-justify\",\"depth\":0,\"inlineStyleRanges\":[],\"entityRanges\":[],\"data\":{}},{\"key\":\"1g3uq\",\"text\":\"\\n \",\"type\":\"unstyled\",\"depth\":0,\"inlineStyleRanges\":[],\"entityRanges\":[],\"data\":{}},{\"key\":\"53dij\",\"text\":\"Homogenization\\n     medium (need 6 ml per sample + ~ 2ml extra for 30% Iodixanol): \",\"type\":\"ordered-list-item\",\"depth\":0,\"inlineStyleRanges\":[{\"style\":\"UNDERLINE\",\"offset\":0,\"length\":83}],\"entityRanges\":[],\"data\":{}},{\"key\":\"aosu\",\"text\":\"\\n \\n  \",\"type\":\"unstyled\",\"depth\":0,\"inlineStyleRanges\":[],\"entityRanges\":[],\"data\":{}},{\"key\":\"4p4v8\",\"text\":\"Recipe\\n      (stable at 4C) for 100 mls / 50 mls\",\"type\":\"ordered-list-item\",\"depth\":1,\"inlineStyleRanges\":[],\"entityRanges\":[],\"data\":{}},{\"key\":\"dct43\",\"text\":\"\\n \",\"type\":\"unstyled\",\"depth\":1,\"inlineStyleRanges\":[],\"entityRanges\":[],\"data\":{}},{\"key\":\"cjr3q\",\"text\":\"1)    .25 M Sucrose (8.56 g / 4.28g) \",\"type\":\"align-justify\",\"depth\":0,\"inlineStyleRanges\":[],\"entityRanges\":[],\"data\":{}},{\"key\":\"apg3d\",\"text\":\"2)    150 mM KCL (7.5 ml / 3.75of\\n2M)\",\"type\":\"align-justify\",\"depth\":0,\"inlineStyleRanges\":[],\"entityRanges\":[],\"data\":{}},{\"key\":\"4kebg\",\"text\":\"3)    5 mM MgCl2 (.5 ml / .25 ml\\nof 1M)\",\"type\":\"align-justify\",\"depth\":0,\"inlineStyleRanges\":[{\"style\":\"sub\",\"offset\":15,\"length\":1}],\"entityRanges\":[],\"data\":{}},{\"key\":\"q5or\",\"text\":\"4)    20 mM Tricine-KOH (2 ml / 1 ml of 1M)\",\"type\":\"align-justify\",\"depth\":0,\"inlineStyleRanges\":[],\"entityRanges\":[],\"data\":{}},{\"key\":\"1e0cc\",\"text\":\"5)    ddH2O up to 100 ml /50 ml in RNAse free H20\",\"type\":\"align-justify\",\"depth\":0,\"inlineStyleRanges\":[{\"style\":\"sub\",\"offset\":9,\"length\":1}],\"entityRanges\":[],\"data\":{}},{\"key\":\"7bnr0\",\"text\":\"\\n \\n  \",\"type\":\"unstyled\",\"depth\":0,\"inlineStyleRanges\":[],\"entityRanges\":[],\"data\":{}},{\"key\":\"e7r0h\",\"text\":\"Supplementation (right\\n      before use): \",\"type\":\"ordered-list-item\",\"depth\":1,\"inlineStyleRanges\":[],\"entityRanges\":[],\"data\":{}},{\"key\":\"2ml5b\",\"text\":\"\\n \",\"type\":\"unstyled\",\"depth\":1,\"inlineStyleRanges\":[],\"entityRanges\":[],\"data\":{}},{\"key\":\"2b1hv\",\"text\":\"1)   \\nFor 4 samples make 35 mls of homogenization buffer\\nand supplement with:\",\"type\":\"align-justify\",\"depth\":0,\"inlineStyleRanges\":[],\"entityRanges\":[],\"data\":{}},{\"key\":\"eijl5\",\"text\":\"1.    \\n3.5 ul spermine, \",\"type\":\"align-justify\",\"depth\":0,\"inlineStyleRanges\":[],\"entityRanges\":[],\"data\":{}},{\"key\":\"73kbd\",\"text\":\"2.    \\n3.5 ul spermidine, \",\"type\":\"align-justify\",\"depth\":0,\"inlineStyleRanges\":[],\"entityRanges\":[],\"data\":{}},{\"key\":\"2t5rn\",\"text\":\"3.    \\n35 ul RNASIN \",\"type\":\"align-justify\",\"depth\":0,\"inlineStyleRanges\":[],\"entityRanges\":[],\"data\":{}},{\"key\":\"7h2mm\",\"text\":\"4.    \\nEDTA free protease inhibitor tablet.\",\"type\":\"align-justify\",\"depth\":0,\"inlineStyleRanges\":[],\"entityRanges\":[],\"data\":{}},{\"key\":\"7mtgc\",\"text\":\" \",\"type\":\"align-justify\",\"depth\":0,\"inlineStyleRanges\":[{\"style\":\"UNDERLINE\",\"offset\":0,\"length\":1}],\"entityRanges\":[],\"data\":{}},{\"key\":\"4u9m2\",\"text\":\"\\n \",\"type\":\"unstyled\",\"depth\":0,\"inlineStyleRanges\":[],\"entityRanges\":[],\"data\":{}},{\"key\":\"fmj5d\",\"text\":\"Iodixanol Dilutions:\",\"type\":\"ordered-list-item\",\"depth\":0,\"inlineStyleRanges\":[{\"style\":\"UNDERLINE\",\"offset\":0,\"length\":20}],\"entityRanges\":[],\"data\":{}},{\"key\":\"6cnu3\",\"text\":\"\\n \\n  \",\"type\":\"unstyled\",\"depth\":0,\"inlineStyleRanges\":[],\"entityRanges\":[],\"data\":{}},{\"key\":\"5v0vt\",\"text\":\"50% Iodixanol \",\"type\":\"ordered-list-item\",\"depth\":1,\"inlineStyleRanges\":[],\"entityRanges\":[],\"data\":{}},{\"key\":\"5i1k0\",\"text\":\"\\n \",\"type\":\"unstyled\",\"depth\":1,\"inlineStyleRanges\":[],\"entityRanges\":[],\"data\":{}},{\"key\":\"99n0l\",\"text\":\"1)   \\nRecipe:\\n5 volumes stock (60%) optiprep + 1 volume of dilutant. \",\"type\":\"align-justify\",\"depth\":0,\"inlineStyleRanges\":[],\"entityRanges\":[],\"data\":{}},{\"key\":\"3dvjj\",\"text\":\"2)   \\nScale:\\nneed 2 ml per sample tube + 3 ml per sample for 35% Iodixanol\",\"type\":\"align-justify\",\"depth\":0,\"inlineStyleRanges\":[],\"entityRanges\":[],\"data\":{}},{\"key\":\"4cs51\",\"text\":\"3)   \\nExample:\\n4 samples add 17.5 ml stock to 3.5 ml dilutant.\",\"type\":\"align-justify\",\"depth\":0,\"inlineStyleRanges\":[],\"entityRanges\":[],\"data\":{}},{\"key\":\"3cnbi\",\"text\":\"\\n \\n  \",\"type\":\"unstyled\",\"depth\":0,\"inlineStyleRanges\":[],\"entityRanges\":[],\"data\":{}},{\"key\":\"4ktis\",\"text\":\"35% Iodixanol \",\"type\":\"ordered-list-item\",\"depth\":1,\"inlineStyleRanges\":[],\"entityRanges\":[],\"data\":{}},{\"key\":\"e6rkb\",\"text\":\"\\n \",\"type\":\"unstyled\",\"depth\":1,\"inlineStyleRanges\":[],\"entityRanges\":[],\"data\":{}},{\"key\":\"48jo1\",\"text\":\"1)   \\nRecipe:\\n7 ml 50% Iodixanol + 3 ml supplemented homogenization medium.\",\"type\":\"align-justify\",\"depth\":0,\"inlineStyleRanges\":[],\"entityRanges\":[],\"data\":{}},{\"key\":\"42jbp\",\"text\":\"2)   \\nScale:\\nneed 4 ml per sample\",\"type\":\"align-justify\",\"depth\":0,\"inlineStyleRanges\":[],\"entityRanges\":[],\"data\":{}},{\"key\":\"7vjam\",\"text\":\"3)   \\nFor\\n4 samples add 5.14 mL supplemented homogenization buffer to 12 mL of 50%\\nIodixanol.\",\"type\":\"align-justify\",\"depth\":0,\"inlineStyleRanges\":[],\"entityRanges\":[],\"data\":{}},{\"key\":\"dlggf\",\"text\":\"\\n \",\"type\":\"unstyled\",\"depth\":0,\"inlineStyleRanges\":[],\"entityRanges\":[],\"data\":{}},{\"key\":\"f8atq\",\"text\":\"Resuspension Buffer for Nuclei Wash (new from 10x\\n     Genomics recipe)\",\"type\":\"ordered-list-item\",\"depth\":0,\"inlineStyleRanges\":[],\"entityRanges\":[],\"data\":{}},{\"key\":\"bff8j\",\"text\":\"                        \\ni.        \\n1x PBS with\\n1.0% BSA and 0.2 U/uL\",\"type\":\"align-justify\",\"depth\":0,\"inlineStyleRanges\":[],\"entityRanges\":[],\"data\":{}},{\"key\":\"9q6ln\",\"text\":\"1)   \\nRecipe:___________\\ncommercial PBS (46-013CM 10x PBS from Corning)\",\"type\":\"align-justify\",\"depth\":0,\"inlineStyleRanges\":[],\"entityRanges\":[],\"data\":{}},{\"key\":\"a8vin\",\"text\":\"2)   \\nRecipe:\\n__________ BSA (001000162 from Jackson Immunoresearch)\",\"type\":\"align-justify\",\"depth\":0,\"inlineStyleRanges\":[],\"entityRanges\":[],\"data\":{}},{\"key\":\"bluj1\",\"text\":\"3)   \\nRecipe:\\n____1:1000______ RNAsin\",\"type\":\"align-justify\",\"depth\":0,\"inlineStyleRanges\":[],\"entityRanges\":[],\"data\":{}},{\"key\":\"9qjmj\",\"text\":\" \",\"type\":\"align-justify\",\"depth\":0,\"inlineStyleRanges\":[],\"entityRanges\":[],\"data\":{}}],\"entityMap\":{\"0\":{\"type\":\"tables\",\"mutability\":\"MUTABLE\",\"data\":{\"cellsMeta\":{\"0_0\":\"\",\"0_1\":\"\",\"0_2\":\"\",\"1_0\":\"\",\"1_1\":\"\",\"1_2\":\"\",\"2_0\":\"\",\"2_1\":\"\",\"2_2\":\"\",\"3_0\":\"\",\"3_1\":\"\",\"3_2\":\"\",\"4_0\":\"\",\"4_1\":\"\",\"4_2\":\"\",\"5_0\":\"\",\"5_1\":\"\",\"5_2\":\"\"},\"colTitles\":[],\"colWidths\":[91,200,134],\"data\":[[\"  \\u003cb style=\\\"mso-bidi-font-weight:normal\\\"\\u003e \\u003c/b\\u003e\\n  \",\"  \\u003cb style=\\\"mso-bidi-font-weight:normal\\\"\\u003e*Diluent Buffer (50mL)\\u003c/b\\u003e\\n  900 mM KCL; 30 mM MgCl2; 120 mM Tricine-KOH (pH\\n  7.8)\\n  \",\"  \\u003cb style=\\\"mso-bidi-font-weight:normal\\\"\\u003e*Homogenization Medium (50mL)\\u003c/b\\u003e\\n  \"],[\"  2M KCl\\n  \",\"  22.5 mL\\n  \",\"  3.75 mL\\n  \"],[\"  1M MgCl2\\n  \",\"  1.5 mL\\n  \",\"  .25 mL\\n  \"],[\"  1M Tricine-KOH\\n  \",\"  6 mL\\n  \",\"  1 mL\\n  \"],[\"  Sucrose\\n  \",\"   \\n  \",\"  4.28 g\\n  \"],[\"  Water\\n  \",\"  20 mL\\n  \",\"  Up to 50 mL\\n  \"]],\"guid\":\"87EBED0031894AA282256F902E154862\",\"isJexcelDataFormat\":true,\"legend\":\"\",\"mergeCells\":[],\"printData\":[[\"  \\u003cb style=\\\"mso-bidi-font-weight:normal\\\"\\u003e \\u003c/b\\u003e\\n  \",\"  \\u003cb style=\\\"mso-bidi-font-weight:normal\\\"\\u003e*Diluent Buffer (50mL)\\u003c/b\\u003e\\n  900 mM KCL; 30 mM MgCl2; 120 mM Tricine-KOH (pH\\n  7.8)\\n  \",\"  \\u003cb style=\\\"mso-bidi-font-weight:normal\\\"\\u003e*Homogenization Medium (50mL)\\u003c/b\\u003e\\n  \"],[\"  2M KCl\\n  \",\"  22.5 mL\\n  \",\"  3.75 mL\\n  \"],[\"  1M MgCl2\\n  \",\"  1.5 mL\\n  \",\"  .25 mL\\n  \"],[\"  1M Tricine-KOH\\n  \",\"  6 mL\\n  \",\"  1 mL\\n  \"],[\"  Sucrose\\n  \",\"   \\n  \",\"  4.28 g\\n  \"],[\"  Water\\n  \",\"  20 mL\\n  \",\"  Up to 50 mL\\n  \"]],\"rowHeights\":[]}},\"1\":{\"type\":\"tables\",\"mutability\":\"MUTABLE\",\"data\":{\"cellsMeta\":{\"0_0\":\"\",\"1_0\":\"\",\"1_1\":\"\",\"1_2\":\"\",\"2_0\":\"\",\"2_1\":\"\",\"2_2\":\"\",\"3_0\":\"\",\"3_1\":\"\",\"3_2\":\"\",\"4_0\":\"\",\"4_1\":\"\",\"4_2\":\"\",\"5_0\":\"\",\"5_1\":\"\",\"5_2\":\"\"},\"colTitles\":[],\"colWidths\":[200],\"data\":[[\"  \\u003cb style=\\\"mso-bidi-font-weight:normal\\\"\\u003eSHB: Supplemented Homogenization Buffer\\n  (prepare right before use)\\u003c/b\\u003e\\n  \",null,null],[\"  Homogenization buffer\\n  \",\"  \\u003cb style=\\\"mso-bidi-font-weight:normal\\\"\\u003e35 mL\\u003c/b\\u003e\\n  \",\"  \\u003cb style=\\\"mso-bidi-font-weight:normal\\\"\\u003e50 mL\\u003c/b\\u003e\\n  \"],[\"  Spermine\\n  \",\"  3.5 ul\\n  \",\"  5.0 ul\\n  \"],[\"  Spermidine\\n  \",\"  3.5 ul\\n  \",\"  5.0 ul\\n  \"],[\"  RNASIN\\n  \",\"  35 ul\\n  \",\"  50 ul\\n  \"],[\"  EDTA free protease inhibitor tablet\\n  \",\"  1\\n  \",\"  2\\n  \"]],\"guid\":\"E6F24067FA4B429CA4FA24FBA53DA686\",\"isJexcelDataFormat\":true,\"legend\":\"\",\"mergeCells\":[],\"printData\":[[\"  \\u003cb style=\\\"mso-bidi-font-weight:normal\\\"\\u003eSHB: Supplemented Homogenization Buffer\\n  (prepare right before use)\\u003c/b\\u003e\\n  \",null,null],[\"  Homogenization buffer\\n  \",\"  \\u003cb style=\\\"mso-bidi-font-weight:normal\\\"\\u003e35 mL\\u003c/b\\u003e\\n  \",\"  \\u003cb style=\\\"mso-bidi-font-weight:normal\\\"\\u003e50 mL\\u003c/b\\u003e\\n  \"],[\"  Spermine\\n  \",\"  3.5 ul\\n  \",\"  5.0 ul\\n  \"],[\"  Spermidine\\n  \",\"  3.5 ul\\n  \",\"  5.0 ul\\n  \"],[\"  RNASIN\\n  \",\"  35 ul\\n  \",\"  50 ul\\n  \"],[\"  EDTA free protease inhibitor tablet\\n  \",\"  1\\n  \",\"  2\\n  \"]],\"rowHeights\":[]}},\"2\":{\"type\":\"tables\",\"mutability\":\"MUTABLE\",\"data\":{\"cellsMeta\":{\"0_0\":\"\",\"1_0\":\"\",\"1_1\":\"\",\"2_0\":\"\",\"2_1\":\"\"},\"colTitles\":[],\"colWidths\":[200],\"data\":[[\"  \\u003cb style=\\\"mso-bidi-font-weight:normal\\\"\\u003e*50% Iodixanol (8 samples)\\u003c/b\\u003e\\n  \",null],[\"  60% Iodixanol\\n  \",\"  35 mL\\n  \"],[\"  Diluent Buffer\\n  \",\"  7 mL\\n  \"]],\"guid\":\"B4E32CAF88604C26AC5C774327EDF808\",\"isJexcelDataFormat\":true,\"legend\":\"\",\"mergeCells\":[],\"printData\":[[\"  \\u003cb style=\\\"mso-bidi-font-weight:normal\\\"\\u003e*50% Iodixanol (8 samples)\\u003c/b\\u003e\\n  \",null],[\"  60% Iodixanol\\n  \",\"  35 mL\\n  \"],[\"  Diluent Buffer\\n  \",\"  7 mL\\n  \"]],\"rowHeights\":[]}},\"3\":{\"type\":\"tables\",\"mutability\":\"MUTABLE\",\"data\":{\"cellsMeta\":{\"0_0\":\"\",\"1_0\":\"\",\"1_1\":\"\",\"2_0\":\"\",\"2_1\":\"\"},\"colTitles\":[],\"colWidths\":[200],\"data\":[[\"  \\u003cb style=\\\"mso-bidi-font-weight:normal\\\"\\u003e35% Iodixanol (8 samples)\\u003c/b\\u003e\\n  \",null],[\"  50% Iodixanol\\n  \",\"  14 mL\\n  \"],[\"  Supplemented Homogenization Buffer\\n  \",\"  6 mL\\n  \"]],\"guid\":\"A267146D57E9448DA1430282E1F2D05D\",\"isJexcelDataFormat\":true,\"legend\":\"\",\"mergeCells\":[],\"printData\":[[\"  \\u003cb style=\\\"mso-bidi-font-weight:normal\\\"\\u003e35% Iodixanol (8 samples)\\u003c/b\\u003e\\n  \",null],[\"  50% Iodixanol\\n  \",\"  14 mL\\n  \"],[\"  Supplemented Homogenization Buffer\\n  \",\"  6 mL\\n  \"]],\"rowHeights\":[]}},\"4\":{\"type\":\"tables\",\"mutability\":\"MUTABLE\",\"data\":{\"cellsMeta\":{\"0_0\":\"\",\"1_0\":\"\",\"1_1\":\"\",\"2_0\":\"\",\"2_1\":\"\",\"3_0\":\"\",\"3_1\":\"\"},\"colTitles\":[],\"colWidths\":[180],\"data\":[[\"  \\u003cb style=\\\"mso-bidi-font-weight:normal\\\"\\u003eNuclei Wash Buffer\\u003c/b\\u003e\\n  1x PBS; 1.5% BSA; .2U/ul RNAsin\\n  \",null],[\"  10x PBS\\n  \",\"  5 mL\\n  \"],[\"  BSA\\n  \",\"  1.5 g\\n  \"],[\"  RNAsin\\n  \",\"  50 uL\\n  \"]],\"guid\":\"11B0CDB83F3244A4A36264A69D8518D1\",\"isJexcelDataFormat\":true,\"legend\":\"\",\"mergeCells\":[],\"printData\":[[\"  \\u003cb style=\\\"mso-bidi-font-weight:normal\\\"\\u003eNuclei Wash Buffer\\u003c/b\\u003e\\n  1x PBS; 1.5% BSA; .2U/ul RNAsin\\n  \",null],[\"  10x PBS\\n  \",\"  5 mL\\n  \"],[\"  BSA\\n  \",\"  1.5 g\\n  \"],[\"  RNAsin\\n  \",\"  50 uL\\n  \"]],\"rowHeights\":[]}}}}",
  "steps": [
    "Protocol: Turn on the ultracentrifuge, set it to 4oC and ensure that decelerations are set to no brake. Get the Beckman SW 60 Ti Rotor (Swinging Bucket) and from the cold room. Beckman centrifuge tubes Ref#=328874 for 4 mLs. Keep all the solutions and materials on wet ice. Prepare of rest of the working solutions. Keep the tubes with the brain samples on dry ice until use. 100-500 mg of brain cortical tissue could yield 1-2 million nuclei. Add pre-chilled 2 mL supplemented homogenization buffer (SHB) to the brain sample and keep it on wet ice. Transfer the brain tissue in 2ml of SHB to a 7 mL Dounce homogenizer. All the samples should be handled equally at all the steps, as different cell types’ nuclei might be more or less vulnerable to physical dissociation. All pipetting and resuspension steps should be gentle and consistent to avoid nuclei shearing and clumping. Homogenize the brain tissue.i.Transfer the brain tissue into a pre-chilled 7 ml Dounce glass homogenizerii.Homogenize with 15 strokes on ice with pre-chilled ‘B’ pestle and 15 with ‘A’ grinder.iii.Transfer the brain lysate into 5 ml microcentrifuge tubes.iv.Add another 2mL SHB to the glass homogenizer and transfer the remaining lysate to the same microcentrifuge tubes. Spin 5 ml microcentrifuge at 500 RCF for 5 minutes at 4o in a swing bucket centrifuge. Pour off the supernatant (optional) Resuspend in 3 mL of SHB. Repeat steps 7 &amp; 8. While spinning, you can add 2 mL of 35% Iodixanol to a centrifuge tube (4 mL, open-top thin-wall polypropylene tube) for each sample. Make sure the Iodixanol is in solution. Resuspend each pellet to a final volume of 1 mL in SHB. Add 1mL of 50% Iodixanol to the samples. Mix 50% Iodixanol right before usage. This step will create 25% Iodixanol with the samples. Pipette the samples up and down with low retention pipette tips (Biotix M-1000-9FC) and carefully layer the sample on top of the 35% Iodixanol solution by slowly into the wall of the tube slightly above the 35 % Iodixanol and making sure the layers do not mix. Centrifuge the tubes at 16,000 RFC for 30 minutes at 4 C. Check decelerations with no brakes again Note: we found that 16,000 RFC brings down endothelial cells from the “myelin layer” more successfully. This brings down vasculature as well and may need to be filtered through a 40um mesh strainer. Carefully remove the centrifuge tubes. The nuclei should be visible as a cloudy layer in the interface of the 25:35% Iodixanol. With a 3 mL plastic Pasteur pipette, remove the top brown layer (myelin/cell debris). Check addendum for parallel work. With a low-retention P1000 tip remove the nuclei from the interface, then place them into a with nonstick, RNase-free microfuge Tubes, 1.5 mL (Cat#: AM12450-Ambion). 750 uLs for 1.5 mL. At this point, a swing bucket rotor is preferable but a fixed angle rotor when using a 1.5mL tube also works. Add Nuclei Wash buffer to fill the tubes &amp; mix by inverting or gently pipetting. Centrifuge at 500 RCF at 4 C. Nuclei should be pelleted at the bottom. Most of the time, the nuclei get stuck to the wall of the 1.5 mL. You could find the nuclei if you pay attention to the orientation of the tube before and after you place it in the microcentrifuge. Remove &amp; discard the supernatant Repeat wash with Nuclei Wash buffer Resuspend nuclei in 1,000 uLs of Nuclei Wash buffer and pass them through a 40 um (70 um also worked) Nylon mesh cell strainer. Take out 10 uLs, mix 1:1 with a 1:2000 DAPI solution, and count on hemacytometer using a fluorescent microscope or Countess® II FL Automated Cell Counter. Check the morphology, size, and absence of nuclei clumps or tissue debris. 10x Genomics recommends an average of four separate readings. Adjust aliquot of nuclei to desired dilution (10x Genomics recommends 1,600 cells per ul for loading onto the controller. If multiplexing, increase concentrations accordingly). Count again to confirm dilution. The rest may be stored as follows: Pellet and resuspend in 10% DMSO in FBS or FCS. Addendum from Step 13. The myelin fraction contains many nuclei and endothelial cells (vasculature). Transfer the myelin/cell fraction to 2ml of SHB to a 7 mL Dounce homogenizer and homogenize with 15 strokes on ice with pre-chilled ‘B’ pestle and 15 with ‘A’ grinder. Transfer the myelin fraction lysate into 5 ml microcentrifuge tubes. Add another 2mL SHB to the glass homogenizer and transfer the remaining lysate to the same microcentrifuge tubes Spin 5 ml microcentrifuge at 500 RCF for 5 minutes at 4o in a swing bucket centrifuge. Pour off the supernatant. Resuspend each pellet to a final volume of 1 mL in SHB. Add 1mL of 50% Iodixanol to the samples. Mix 50% Iodixanol right before usage. Add 2 mL of 35% Iodixanol to a centrifuge tube. Pipette the samples up and down with low retention pipette tips (Biotix M-1000-9FC) and carefully layer the sample on top of the 35% Iodixanol solution and making sure the layers do not mix. Centrifuge the tubes at 16,000 RFC for 30 minutes at 4 C with no brakes. With a low-retention P1000 tip remove the nuclei from the interface (750 uLs), then place them into a 1.5mL nonstick, RNase-free microfuge Tubes, 1.5 mL (Cat#: AM12450-Ambion) and add Nuclei Wash buffer to fill the tubes &amp; mix by inverting or gently pipetting. Centrifuge at 500 RCF at 4 C. Nuclei should be pelleted at the bottom. Most of the time, the nuclei get stuck to the wall of the 1.5 mL. Remove &amp; discard the supernatant Repeat wash with Nuclei Wash buffer Resuspend nuclei in 1,000 uLs of Nuclei Wash buffer and pass them through a 70 um Nylon mesh cell strainer. Take out 10 uLs, mix 1:1 with a 1:2000 DAPI solution, and count them. Adjust aliquot of nuclei to desired dilution. Count again to confirm dilution. The rest may be stored as follows: Pellet and resuspend in 10% DMSO in FBS or FCS."
  ],
  "authors": [
    "Bruno A. Benitez"
  ],
  "creator": "Bruno A. Benitez",
  "published_on": 1706123730,
  "created_on": 1705604199,
  "keywords": []
}